{"_type":"export","__export_format":4,"__export_date":"2021-10-24T00:33:48.103Z","__export_source":"insomnia.desktop.app:v2021.5.3","resources":[{"_id":"req_d1c838915ad546fa885ed8cd5a8b053f","parentId":"fld_cb9c5818af124ec58238f4b5e6aed17a","modified":1635035460870,"created":1635035434429,"url":"{{ _.base_url }}/fourier","name":"ValidExpression","description":"","method":"POST","body":{"mimeType":"application/json","text":"{\n\t\"first_interval\": -3.14,\n\t\"second_interval\": 3.14,\n\t\"expression\": \"x + 1\",\n\t\"n\": 3\n}"},"parameters":[],"headers":[{"name":"Content-Type","value":"application/json","id":"pair_46d571ccf638432486c7a8b2b1eabebe"}],"authentication":{},"metaSortKey":-1635035434429,"isPrivate":false,"settingStoreCookies":true,"settingSendCookies":true,"settingDisableRenderRequestBody":false,"settingEncodeUrl":true,"settingRebuildPath":true,"settingFollowRedirects":"global","_type":"request"},{"_id":"fld_cb9c5818af124ec58238f4b5e6aed17a","parentId":"wrk_3ba59c44601b4912a6549d920d7493c1","modified":1635034501985,"created":1635034501985,"name":"Fourier","description":"","environment":{},"environmentPropertyOrder":null,"metaSortKey":-1635034501985,"_type":"request_group"},{"_id":"wrk_3ba59c44601b4912a6549d920d7493c1","parentId":null,"modified":1632355846541,"created":1632355846541,"name":"CN","description":"","scope":"collection","_type":"workspace"},{"_id":"req_b57ad2928b8d4b18ad55f834ea28dcb7","parentId":"fld_cb9c5818af124ec58238f4b5e6aed17a","modified":1635035446883,"created":1635035394873,"url":"{{ _.base_url }}/fourier","name":"ValidExpression","description":"","method":"POST","body":{"mimeType":"application/json","text":"{\n\t\"first_interval\": -3.14,\n\t\"second_interval\": 3.14,\n\t\"expression\": \"x + y + 1\",\n\t\"n\": 3\n}"},"parameters":[],"headers":[{"name":"Content-Type","value":"application/json","id":"pair_aaf583acf408410d9d5a40eb81b749c8"}],"authentication":{},"metaSortKey":-1635035394873,"isPrivate":false,"settingStoreCookies":true,"settingSendCookies":true,"settingDisableRenderRequestBody":false,"settingEncodeUrl":true,"settingRebuildPath":true,"settingFollowRedirects":"global","_type":"request"},{"_id":"req_08ee667bf18c4f6baf77fb135ec8a802","parentId":"fld_cb9c5818af124ec58238f4b5e6aed17a","modified":1635035357044,"created":1635035328687,"url":"{{ _.base_url }}/fourier","name":"MissingX","description":"","method":"POST","body":{"mimeType":"application/json","text":"{\n\t\"first_interval\": -3.14,\n\t\"second_interval\": 3.14,\n\t\"expression\": \"y + 1\",\n\t\"n\": 3\n}"},"parameters":[],"headers":[{"name":"Content-Type","value":"application/json","id":"pair_5dcd483448944c5080ef851019a061bd"}],"authentication":{},"metaSortKey":-1635035328687,"isPrivate":false,"settingStoreCookies":true,"settingSendCookies":true,"settingDisableRenderRequestBody":false,"settingEncodeUrl":true,"settingRebuildPath":true,"settingFollowRedirects":"global","_type":"request"},{"_id":"req_e18b613d44884a3da995b598ddde6a44","parentId":"fld_cb9c5818af124ec58238f4b5e6aed17a","modified":1635035316077,"created":1635034508558,"url":"{{ _.base_url }}/fourier","name":"InvalidInterval","description":"","method":"POST","body":{"mimeType":"application/json","text":"{\n\t\"first_interval\": 3.14,\n\t\"second_interval\": 3.14,\n\t\"expression\": \"x + 1\",\n\t\"n\": 3\n}"},"parameters":[],"headers":[{"name":"Content-Type","value":"application/json","id":"pair_61976bbb6164435abd39db58213fd9d2"}],"authentication":{},"metaSortKey":-1635034508558,"isPrivate":false,"settingStoreCookies":true,"settingSendCookies":true,"settingDisableRenderRequestBody":false,"settingEncodeUrl":true,"settingRebuildPath":true,"settingFollowRedirects":"global","_type":"request"},{"_id":"req_a9b78e7c3f6349f696969ca6688663b8","parentId":"wrk_3ba59c44601b4912a6549d920d7493c1","modified":1632356254916,"created":1632356240921,"url":"{{ _.base_url }}/sums/johndoe","name":"YourNameWithParams","description":"","method":"GET","body":{},"parameters":[],"headers":[],"authentication":{},"metaSortKey":-1632356240921,"isPrivate":false,"settingStoreCookies":true,"settingSendCookies":true,"settingDisableRenderRequestBody":false,"settingEncodeUrl":true,"settingRebuildPath":true,"settingFollowRedirects":"global","_type":"request"},{"_id":"req_3c63112af1ab46d3a8224f811a119faf","parentId":"wrk_3ba59c44601b4912a6549d920d7493c1","modified":1632356219409,"created":1632356182153,"url":"{{ _.base_url }}/sums/query?value1=2&value2=3","name":"SumWithQuery","description":"","method":"GET","body":{},"parameters":[],"headers":[],"authentication":{},"metaSortKey":-1632356182153,"isPrivate":false,"settingStoreCookies":true,"settingSendCookies":true,"settingDisableRenderRequestBody":false,"settingEncodeUrl":true,"settingRebuildPath":true,"settingFollowRedirects":"global","_type":"request"},{"_id":"req_37e1587fbe114dc6a1888f93f014af58","parentId":"wrk_3ba59c44601b4912a6549d920d7493c1","modified":1632359413521,"created":1632355852562,"url":"http://localhost:5000/sums/","name":"SumWithBody","description":"","method":"POST","body":{"mimeType":"application/json","text":"{\n\t\"sum1\": 1,\n\t\"sum2\": 3\n}"},"parameters":[],"headers":[{"name":"Content-Type","value":"application/json","id":"pair_8d368f916cd441baa481adbd193cecff"}],"authentication":{},"metaSortKey":-1632355852562,"isPrivate":false,"settingStoreCookies":true,"settingSendCookies":true,"settingDisableRenderRequestBody":false,"settingEncodeUrl":true,"settingRebuildPath":true,"settingFollowRedirects":"global","_type":"request"},{"_id":"env_a391501d96317610c917d4b6ca393f8fe7791d1f","parentId":"wrk_3ba59c44601b4912a6549d920d7493c1","modified":1632356198384,"created":1632355846553,"name":"Base Environment","data":{"base_url":"http://localhost:5000"},"dataPropertyOrder":{"&":["base_url"]},"color":null,"isPrivate":false,"metaSortKey":1632355846553,"_type":"environment"},{"_id":"jar_a391501d96317610c917d4b6ca393f8fe7791d1f","parentId":"wrk_3ba59c44601b4912a6549d920d7493c1","modified":1632355846555,"created":1632355846555,"name":"Default Jar","cookies":[],"_type":"cookie_jar"},{"_id":"spc_5d970b9eed4042d38be53788105747a7","parentId":"wrk_3ba59c44601b4912a6549d920d7493c1","modified":1632355846547,"created":1632355846547,"fileName":"CN","contents":"","contentType":"yaml","_type":"api_spec"}]}